{
  "type": "minecraft:multi_action",
  "title": "Smashing",
  "body": [
    {
      "type": "minecraft:plain_message",
      "contents": "Arrows and Tridents can break more blocks!",
      "width": 300
    },
    {
      "type": "minecraft:plain_message",
      "contents": {
        "text": "v1.2.0\nBy runcows",
        "color": "gray"
      },
      "width": 300
    },
    {
      "type": "minecraft:plain_message",
      "contents": [
        "",
        {
          "text": "Arrow Breakable:\n\n",
          "bold": true,
          "underlined": true
        },
        " Candles        ",
        " Cakes           ",
        " Cactus\n ",
        " Flower Pots    ",
        " Glass Panes   ",
        " Sea Pickle\n",
        " Big Dripleaf      ",
        " Lily Pad        ",
        " Melon    \n       ",
        " Pumpkin       ",
        " Carved Pumpkin  ",
        " Jack o'Lantern"
      ],
      "width": 300
    },
    {
      "type": "minecraft:plain_message",
      "contents": [
        "",
        {
          "text": "Trident Breakable:\n\n",
          "bold": true,
          "underlined": true
        },
        "Everything an arrow can break and...\n",
        " Bamboo\n",
        " Cocoa Beans\n",
        " Dried Ghast\n",
        " Amethyst Clusters & Buds"
      ],
      "width": 300
    }
  ],
  "actions": [
    {
      "label": "Issues",
      "action": {
        "type": "open_url",
        "url": "https://github.com/runcows/smashing/issues"
      }
    }
  ],
  "exit_action": {
    "action": {
      "type": "show_dialog",
      "dialog": "smithed:data_packs"
    },
    "label": {
      "translate": "gui.back"
    },
    "width": 200
  }
}
